Workbook

Sheet Assumptions
A1: MarkReady — Year 1 Financial Model: Conservative Assumptions
A2: All figures USD. HK compliance costs converted from HKD at 7.8 peg. Blue cells = editable inputs.
A4: Assumption | B4: Value | C4: Basis / note
A5: Free → paid conversion rate | B5: 0.025 | C5: Low end of freemium 2-5% range
A6: Monthly churn (paying users) | B6: 0.15 | C6: High - exam products churn on test completion
A7: Blended ARPU (USD/mo) | B7: 12 | C7: Philippines-first; regional pricing dominates
A8: Essays scored per new free signup | B8: 2 | C8: Most free users try it once or twice
A9: Essays scored per paying user / mo | B9: 8 | C9: Active paying users practising regularly
A10: API / scoring cost per essay (USD) | B10: 0.02 | C10: Per your noted ~2 cents/call
A11: Payment processing fee (% of revenue) | B11: 0.05 | C11: ~3%+fixed, higher for intl cards - rounded up

Sheet Year 1 Monthly Model
A1: MarkReady — Year 1 Monthly P&L (Conservative Base Case)
A3: Line item (USD) | B3: M1 | C3: M2 | D3: M3 | E3: M4 | F3: M5 | G3: M6 | H3: M7 | I3: M8 | J3: M9 | K3: M10 | L3: M11 | M3: M12 | N3: Year 1 Total
A4: USERS & REVENUE
A5: New free signups | B5: 60 | C5: 120 | D5: 200 | E5: 300 | F5: 400 | G5: 500 | H5: 600 | I5: 700 | J5: 800 | K5: 900 | L5: 1000 | M5: 1100 | N5: =SUM(B5:M5) -> 6680
A6: Cumulative free users | B6: =B5 -> 60 | C6: =B6+C5 -> 180 | D6: =C6+D5 -> 380 | E6: =D6+E5 -> 680 | F6: =E6+F5 -> 1080 | G6: =F6+G5 -> 1580 | H6: =G6+H5 -> 2180 | I6: =H6+I5 -> 2880 | J6: =I6+J5 -> 3680 | ... M6: =L6+M5 -> 6680 | N6: =M6 -> 6680
A7: New paid conversions | B7: 0 | C7: =ROUND(Assumptions!$B$5*(C5+B5),0) -> 5 | D7: =ROUND(Assumptions!$B$5*D5,0) -> 5 | E7: =ROUND(Assumptions!$B$5*E5,0) -> 8 | F7: =ROUND(Assumptions!$B$5*F5,0) -> 10 | G7: =ROUND(Assumptions!$B$5*G5,0) -> 13 | H7: =ROUND(Assumptions!$B$5*H5,0) -> 15 | I7: =ROUND(Assumptions!$B$5*I5,0) -> 18 | J7: =ROUND(Assumptions!$B$5*J5,0) -> 20 | K7: =ROUND(Assumptions!$B$5*K5,0) -> 23 | ... M7: =ROUND(Assumptions!$B$5*M5,0) -> 28 | N7: =SUM(B7:M7) -> 170
A8: Paying users (end of month) | B8: =B7 -> 0 | C8: =ROUND(B8*(1-Assumptions!$B$6)+C7,0) -> 5 | D8: =ROUND(C8*(1-Assumptions!$B$6)+D7,0) -> 9 | E8: =ROUND(D8*(1-Assumptions!$B$6)+E7,0) -> 16 | F8: =ROUND(E8*(1-Assumptions!$B$6)+F7,0) -> 24 | G8: =ROUND(F8*(1-Assumptions!$B$6)+G7,0) -> 33 | H8: =ROUND(G8*(1-Assumptions!$B$6)+H7,0) -> 43 | I8: =ROUND(H8*(1-Assumptions!$B$6)+I7,0) -> 55 | J8: =ROUND(I8*(1-Assumptions!$B$6)+J7,0) -> 67 | ... M8: =ROUND(L8*(1-Assumptions!$B$6)+M7,0) -> 107 | N8: =M8 -> 107
A9: MRR (paying x ARPU) | B9: =B8*Assumptions!$B$7 -> 0 | C9: =C8*Assumptions!$B$7 -> 60 | D9: =D8*Assumptions!$B$7 -> 108 | E9: =E8*Assumptions!$B$7 -> 192 | F9: =F8*Assumptions!$B$7 -> 288 | G9: =G8*Assumptions!$B$7 -> 396 | H9: =H8*Assumptions!$B$7 -> 516 | I9: =I8*Assumptions!$B$7 -> 660 | ... M9: =M8*Assumptions!$B$7 -> 1284 | N9: =M9 -> 1284
A10: Revenue (recognized this month) | B10: =B9 -> 0 | C10: =C9 -> 60 | D10: =D9 -> 108 | E10: =E9 -> 192 | F10: =F9 -> 288 | G10: =G9 -> 396 | H10: =H9 -> 516 | I10: =I9 -> 660 | ... M10: =M9 -> 1284 | N10: =SUM(B10:M10) -> 6384
A11: VARIABLE COSTS
A12: API / scoring cost | B12: =(B5*Assumptions!$B$8+B8*Assumptions!$B$9)*Assumptions!$B$10 -> 2.4 | C12: =(C5*Assumptions!$B$8+C8*Assumptions!$B$9)*Assumptions!$B$10 -> 5.6 | D12: =(D5*Assumptions!$B$8+D8*Assumptions!$B$9)*Assumptions!$B$10 -> 9.44 | E12: =(E5*Assumptions!$B$8+E8*Assumptions!$B$9)*Assumptions!$B$10 -> 14.56 | F12: =(F5*Assumptions!$B$8+F8*Assumptions!$B$9)*Assumptions!$B$10 -> 19.84 | G12: =(G5*Assumptions!$B$8+G8*Assumptions!$B$9)*Assumptions!$B$10 -> 25.28 | H12: =(H5*Assumptions!$B$8+H8*Assumptions!$B$9)*Assumptions!$B$10 -> 30.88 | I12: =(I5*Assumptions!$B$8+I8*Assumptions!$B$9)*Assumptions!$B$10 -> 36.8 | ... M12: =(M5*Assumptions!$B$8+M8*Assumptions!$B$9)*Assumptions!$B$10 -> 61.12 | N12: =SUM(B12:M12) -> 352.32
A13: Payment processing fees | B13: =B10*Assumptions!$B$11 -> 0 | C13: =C10*Assumptions!$B$11 -> 3 | D13: =D10*Assumptions!$B$11 -> 5.4 | E13: =E10*Assumptions!$B$11 -> 9.6 | F13: =F10*Assumptions!$B$11 -> 14.4 | G13: =G10*Assumptions!$B$11 -> 19.8 | H13: =H10*Assumptions!$B$11 -> 25.8 | I13: =I10*Assumptions!$B$11 -> 33 | ... M13: =M10*Assumptions!$B$11 -> 64.2 | N13: =SUM(B13:M13) -> 319.2
A14: RECURRING FIXED COSTS
A15: Hosting & infrastructure | B15: 0 | C15: 0 | D15: 0 | E15: 50 | F15: 50 | G15: 50 | H15: 100 | I15: 100 | J15: 100 | K15: 100 | L15: 100 | M15: 100 | N15: =SUM(B15:M15) -> 750
A16: AI coding tools (Claude Code etc.) | B16: 100 | C16: 100 | D16: 100 | E16: 100 | F16: 100 | G16: 100 | H16: 100 | I16: 100 | J16: 100 | K16: 100 | L16: 100 | M16: 100 | N16: =SUM(B16:M16) -> 1200
A17: Marketing (content, creators, tools) | B17: 150 | C17: 150 | D17: 150 | E17: 300 | F17: 300 | G17: 300 | H17: 300 | I17: 300 | J17: 300 | K17: 300 | L17: 300 | M17: 300 | N17: =SUM(B17:M17) -> 3150
A18: HK compliance (recurring, amortized) | B18: 320 | C18: 320 | D18: 320 | E18: 320 | F18: 320 | G18: 320 | H18: 320 | I18: 320 | J18: 320 | K18: 320 | L18: 320 | M18: 320 | N18: =SUM(B18:M18) -> 3840
A19: ONE-OFF COSTS (Year 1)
A20: HK incorporation (setup, bundled) | B20: 1300 | C20: 0 | D20: 0 | E20: 0 | F20: 0 | G20: 0 | H20: 0 | I20: 0 | J20: 0 | K20: 0 | L20: 0 | M20: 0 | N20: =SUM(B20:M20) -> 1300
A21: Freelance dev — V1 accounts/billing | B21: 1500 | C21: 1500 | D21: 0 | E21: 0 | F21: 0 | G21: 0 | H21: 0 | I21: 0 | J21: 0 | K21: 0 | L21: 0 | M21: 0 | N21: =SUM(B21:M21) -> 3000
A22: Legal — ToS / privacy | B22: 400 | C22: 0 | D22: 0 | E22: 0 | F22: 0 | G22: 0 | H22: 0 | I22: 0 | J22: 0 | K22: 0 | L22: 0 | M22: 0 | N22: =SUM(B22:M22) -> 400
A23: Brand / logo | B23: 150 | C23: 0 | D23: 0 | E23: 0 | F23: 0 | G23: 0 | H23: 0 | I23: 0 | J23: 0 | K23: 0 | L23: 0 | M23: 0 | N23: =SUM(B23:M23) -> 150
A24: Domain & initial setup | B24: 100 | C24: 0 | D24: 0 | E24: 0 | F24: 0 | G24: 0 | H24: 0 | I24: 0 | J24: 0 | K24: 0 | L24: 0 | M24: 0 | N24: =SUM(B24:M24) -> 100
A25: TOTALS
A26: Total costs | B26: =B12+B13+B15+B16+B17+B18+B20+B21+B22+B23+B24 -> 4022.4 | C26: =C12+C13+C15+C16+C17+C18+C20+C21+C22+C23+C24 -> 2078.6 | D26: =D12+D13+D15+D16+D17+D18+D20+D21+D22+D23+D24 -> 584.84 | E26: =E12+E13+E15+E16+E17+E18+E20+E21+E22+E23+E24 -> 794.16 | F26: =F12+F13+F15+F16+F17+F18+F20+F21+F22+F23+F24 -> 804.24 | G26: =G12+G13+G15+G16+G17+G18+G20+G21+G22+G23+G24 -> 815.08 | H26: =H12+H13+H15+H16+H17+H18+H20+H21+H22+H23+H24 -> 876.68 | I26: =I12+I13+I15+I16+I17+I18+I20+I21+I22+I23+I24 -> 889.8 | ... M26: =M12+M13+M15+M16+M17+M18+M20+M21+M22+M23+M24 -> 945.32 | N26: =SUM(B26:M26) -> 14561.52
A27: Net profit / (loss) | B27: =B10-B26 -> -4022.4 | C27: =C10-C26 -> -2018.6 | D27: =D10-D26 -> -476.84 | E27: =E10-E26 -> -602.16 | F27: =F10-F26 -> -516.24 | G27: =G10-G26 -> -419.08 | H27: =H10-H26 -> -360.68 | I27: =I10-I26 -> -229.8 | ... N27: =N10-N26 -> -8177.52
A28: Operating profit excl. one-off | B28: =B10-(B12+B13+B15+B16+B17+B18) -> -572.4 | C28: =C10-(C12+C13+C15+C16+C17+C18) -> -518.6 | D28: =D10-(D12+D13+D15+D16+D17+D18) -> -476.84 | E28: =E10-(E12+E13+E15+E16+E17+E18) -> -602.16 | F28: =F10-(F12+F13+F15+F16+F17+F18) -> -516.24 | G28: =G10-(G12+G13+G15+G16+G17+G18) -> -419.08 | H28: =H10-(H12+H13+H15+H16+H17+H18) -> -360.68 | I28: =I10-(I12+I13+I15+I16+I17+I18) -> -229.8 | ... M28: =M10-(M12+M13+M15+M16+M17+M18) -> 338.68
A29: Cumulative cash position | B29: =B27 -> -4022.4 | C29: =B29+C27 -> -6041 | D29: =C29+D27 -> -6517.84 | E29: =D29+E27 -> -7120 | F29: =E29+F27 -> -7636.24 | G29: =F29+G27 -> -8055.32 | H29: =G29+H27 -> -8416 | I29: =H29+I27 -> -8645.8 | J29: =I29+J27 -> -8744.72 | ... M29: =L29+M27 -> -8177.52 | N29: =M29 -> -8177.52

Sheet Summary
A1: MarkReady — Year 1 Summary (Conservative Base Case)
A3: Metric | B3: Year 1 value | C3: Note
A4: Total revenue | B4: ='Year 1 Monthly Model'!N10 -> 6384 | C4: Sum of monthly MRR
A5: Total costs | B5: ='Year 1 Monthly Model'!N26 -> 14561.52 | C5: One-off + recurring + variable
A6: Net result (Year 1) | B6: ='Year 1 Monthly Model'!N27 -> -8177.52 | C6: Expect a loss in Year 1
A7: Ending paying users (M12) | B7: ='Year 1 Monthly Model'!M8 -> 107 | C7: After 15% monthly churn
A8: Ending MRR (M12) | B8: ='Year 1 Monthly Model'!M9 -> 1284 | C8: Run-rate exiting Year 1
A9: Ending cumulative cash | B9: ='Year 1 Monthly Model'!M29 -> -8177.52 | C9: Total out-of-pocket funded
A10: Cumulative free users (M12) | B10: ='Year 1 Monthly Model'!M6 -> 6680 | C10: Top of funnel
A12: How to read this model
A13: - This is a deliberately conservative BASE case. Treat it as a floor, not a forecast.
A14: - B2B prep-centre revenue is set to ZERO here - it is upside, not assumed.
A15: - Year 1 ends with an operational monthly profit but a cumulative loss, because one-off build + setup costs are front-loaded.
A16: - To model a BULL case: raise conversion to 4%, ARPU to $16, churn to 12%, and roughly double free signups.
A17: - To model a BEAR case: drop conversion to 1.5%, raise churn to 18%, halve free signups.
A18: - All inputs are the yellow/blue cells on the Assumptions tab and the signup/cost rows in the model.
